{
    "ok":  true,
    "versionCode":  49,
    "versionName":  "1.3.2",
    "buildId":  "dba536e39b52bd5b492c8b15c4c8a267",
    "publishedAt":  1782783078061,
    "changelog":  "v1.3.2 hotfix: location page uses real GPS address",
    "downloadUrl":  "https://ghproxy.net/https://raw.githubusercontent.com/liu202612/leiliao/main/leiliao.apk?v=dba536e39b52bd5b492c8b15c4c8a267",
    "mirrorApkUrls":  [
                          "https://ghproxy.net/https://raw.githubusercontent.com/liu202612/leiliao/main/leiliao.apk?v=dba536e39b52bd5b492c8b15c4c8a267",
                          "https://raw.githubusercontent.com/liu202612/leiliao/main/leiliao.apk?v=dba536e39b52bd5b492c8b15c4c8a267",
                          "https://cdn.jsdelivr.net/gh/liu202612/leiliao@main/leiliao.apk?v=dba536e39b52bd5b492c8b15c4c8a267"
                      ],
    "hasUpdate":  false
}
